rrtask/__init__.py
rrtask/enums.py
rrtask/rrtask.py
rrtask/signals.py
rrtask/utils.py
rrtask/version.py
rrtask-2.1.0.dist-info/LICENSE
rrtask-2.1.0.dist-info/METADATA
rrtask-2.1.0.dist-info/WHEEL
rrtask-2.1.0.dist-info/RECORD
