Metadata-Version: 2.3
Name: rrtask
Version: 2.1.0
Summary: Round Robin Task
License: MIT
Requires-Python: >=3.9
Classifier: License :: OSI Approved :: MIT License
Classifier: Programming Language :: Python :: 3
Classifier: Programming Language :: Python :: 3.9
Classifier: Programming Language :: Python :: 3.10
Classifier: Programming Language :: Python :: 3.11
Classifier: Programming Language :: Python :: 3.12
Classifier: Programming Language :: Python :: 3.13
Requires-Dist: blinker
Requires-Dist: celery
Requires-Dist: pyrabbit
Requires-Dist: redis
